{"leader":"01561ncm a2200409 i 4500","fields":[{"001":"a2499"},{"003":"SIRSI"},{"005":"20180217050003.0"},{"008":"820518s1980    miua          000 0 eng  "},{"010":{"ind1":" ","ind2":" ","subfields":[{"a":"   80022474/MN"}]}},{"020":{"ind1":" ","ind2":" ","subfields":[{"a":"0835711374 (set) :"},{"c":"$59.95"}]}},{"020":{"ind1":" ","ind2":" ","subfields":[{"a":"0835711390 (v. 2)"}]}},{"020":{"ind1":" ","ind2":" ","subfields":[{"a":"9780835711371 (set)"}]}},{"020":{"ind1":" ","ind2":" ","subfields":[{"a":"9780835711395 (v. 2)"}]}},{"035":{"ind1":" ","ind2":" ","subfields":[{"a":"(OCoLC-M)268710340"}]}},{"035":{"ind1":" ","ind2":" ","subfields":[{"a":"(OCoLC-I)268823295"}]}},{"040":{"ind1":" ","ind2":" ","subfields":[{"d":"OrLoB"}]}},{"050":{"ind1":"0","ind2":" ","subfields":[{"a":"ML96.4"},{"b":".B4"}]}},{"082":{"ind1":"0","ind2":" ","subfields":[{"a":"780.8/1"},{"2":"19"}]}},{"100":{"ind1":"1","ind2":" ","subfields":[{"a":"Johnson, Douglas Porter."},{"=":"^A190525"}]}},{"245":{"ind1":"1","ind2":"0","subfields":[{"a":"Beethoven's early sketches in the \"Fischhof miscellany,\" Berlin Autograph 28 /"},{"c":"by Douglas Porter Johnson."}]}},{"260":{"ind1":" ","ind2":" ","subfields":[{"a":"Ann Arbor, Mich. :"},{"b":"UMI Research Press,"},{"c":"c1980-"}]}},{"300":{"ind1":" ","ind2":" ","subfields":[{"a":"2 v. :"},{"b":"ill. ;"},{"c":"24-29 cm."}]}},{"500":{"ind1":" ","ind2":" ","subfields":[{"a":"\"Transcriptions\": v. 2, p. 3-201."}]}},{"504":{"ind1":" ","ind2":" ","subfields":[{"a":"Bibliography: v.1, p. [511]-516."}]}},{"596":{"ind1":" ","ind2":" ","subfields":[{"a":"18"}]}},{"600":{"ind1":"1","ind2":"0","subfields":[{"a":"Beethoven, Ludwig van,"},{"d":"1770-1827."},{"t":"Works."},{"k":"Selections (Sketches)"},{"=":"^A958635"}]}},{"650":{"ind1":" ","ind2":"0","subfields":[{"a":"Musical sketches."},{"=":"^A1041892"}]}},{"700":{"ind1":"1","ind2":"2","subfields":[{"a":"Beethoven, Ludwig van,"},{"d":"1770-1827."},{"t":"Works."},{"k":"Selections (Sketches)."},{"=":"^A958635"}]}},{"740":{"ind1":"0","ind2":" ","subfields":[{"a":"Fischhof miscellany."}]}},{"916":{"ind1":" ","ind2":" ","subfields":[{"a":"DATE CATALOGED"},{"b":"19900927"}]}},{"942":{"ind1":" ","ind2":" ","subfields":[{"s":"a"},{"a":"xtn"}]}},{"852":{"ind1":" ","ind2":" ","subfields":[{"a":"CSt"},{"b":"MUSIC"},{"c":"STACKS"}]}},{"866":{"ind1":" ","ind2":"0","subfields":[{"8":"1"},{"a":"v.1"}]}},{"866":{"ind1":" ","ind2":"0","subfields":[{"8":"1"},{"a":"v.2"}]}},{"999":{"ind1":" ","ind2":" ","subfields":[{"a":"ML96.4 .B415 NO.6:V.1"},{"w":"LC"},{"c":"1"},{"i":"36105041862777"},{"d":"5/20/2013"},{"e":"11/16/2010"},{"l":"STACKS"},{"m":"MUSIC"},{"n":"4"},{"q":"1"},{"r":"Y"},{"s":"Y"},{"t":"STKS"},{"u":"5/18/1982"},{"z":"DIGI-SENT"}]}},{"999":{"ind1":" ","ind2":" ","subfields":[{"a":"ML96.4 .B415 NO.6:V.2"},{"w":"LC"},{"c":"1"},{"i":"36105004284639"},{"d":"5/20/2013"},{"e":"11/16/2010"},{"l":"STACKS"},{"m":"MUSIC"},{"n":"4"},{"q":"1"},{"r":"Y"},{"s":"Y"},{"t":"STKS"},{"u":"5/18/1982"},{"z":"DIGI-SENT"}]}}]}
