{"cocinaVersion":"0.75.0","type":"https://cocina.sul.stanford.edu/models/collection","externalIdentifier":"druid:bf420qj4978","label":"Travel through Time: Japan","version":3,"access":{"view":"world","useAndReproductionStatement":"Property rights reside with the repository. To obtain permission to publish or reproduce, please contact the East Asia Library at eastasialibrary@stanford.edu."},"administrative":{"hasAdminPolicy":"druid:xw330hm5827"},"description":{"title":[{"structuredValue":[],"parallelValue":[],"groupedValue":[],"value":"Travel through Time: Japan","identifier":[],"note":[],"appliesTo":[]}],"contributor":[],"event":[],"form":[],"geographic":[],"language":[],"note":[{"structuredValue":[],"parallelValue":[],"groupedValue":[],"value":"Images from a collection of materials related to travel in Japan between 17th century and the early 20th century. It includes a wide assortment of items that were collected by travelers or created by artists to encourage travel to famous destinations. The collection is especially notable for its souvenir prints, such as keidaizu and onsenzu, various types of practical maps, such as route maps and transit maps for pilgrims, as well as religious ephemera, such as butsuhanga, mandara, and sangoku denrai.","type":"abstract","identifier":[],"note":[],"appliesTo":[]}],"identifier":[],"subject":[],"relatedResource":[],"marcEncodedData":[],"purl":"https://purl.stanford.edu/bf420qj4978"},"identification":{"catalogLinks":[]},"created":"2022-04-26T19:21:00.000+00:00","modified":"2024-06-13T09:37:11.000+00:00","lock":"druid:bf420qj4978=0=1"}